LICENSE
README.md
run_SC18_SRC.py
setup.py
tablegen.py
test.c
.idea/vcs.xml
asmjit/__init__.py
asmjit/__main__.py
asmjit/bench.py
asmjit/oldjit.py
asmjit/op.py
asmjit/sc18src.py
asmjit.egg-info/PKG-INFO
asmjit.egg-info/SOURCES.txt
asmjit.egg-info/dependency_links.txt
asmjit.egg-info/requires.txt
asmjit.egg-info/top_level.txt
dev_test/x86_add_ir64_lat1.ll
dev_test/x86_add_ir64_lat12.ll
dev_test/x86_add_ir64_tp12.ll