Metadata-Version: 2.1
Name: asmjit
Version: 0.1.1
Summary: A Benchmark Toolkit for Assembly Instructions Using the LLVM JIT
Home-page: UNKNOWN
Author: Julian Hammer
Author-email: julian.hammer@u-sys.org
License: AGPLv3
Platform: UNKNOWN
